fissa/__init__.py
fissa/__meta__.py
fissa/core.py
fissa/deltaf.py
fissa/extraction.py
fissa/neuropil.py
fissa/polygons.py
fissa/readimagejrois.py
fissa/roitools.py
fissa-1.0.0.dist-info/LICENSE
fissa-1.0.0.dist-info/METADATA
fissa-1.0.0.dist-info/WHEEL
fissa-1.0.0.dist-info/top_level.txt
fissa-1.0.0.dist-info/RECORD
